doublify_toolkit-0.5.2-py3.6-nspkg.pth
doublify/toolkit/__init__.py
doublify/toolkit/filtering/__init__.py
doublify/toolkit/filtering/tokenizer.py
doublify_toolkit-0.5.2.dist-info/DESCRIPTION.rst
doublify_toolkit-0.5.2.dist-info/METADATA
doublify_toolkit-0.5.2.dist-info/RECORD
doublify_toolkit-0.5.2.dist-info/WHEEL
doublify_toolkit-0.5.2.dist-info/metadata.json
doublify_toolkit-0.5.2.dist-info/namespace_packages.txt
doublify_toolkit-0.5.2.dist-info/top_level.txt
