Metadata-Version: 2.0
Name: doublify-toolkit
Version: 0.5.2
Summary: Doublify API toolkit for Python
Home-page: https://github.com/doublifyapis/toolkit-python
Author: Doublify Technologies
Author-email: apis+opensource@doublify.io
License: MIT
Keywords: doublify toolkit
Platform: UNKNOWN
Classifier: Development Status :: 3 - Alpha
Classifier: Intended Audience :: Developers
Classifier: Intended Audience :: Science/Research
Classifier: Intended Audience :: System Administrators
Classifier: Intended Audience :: Telecommunications Industry
Classifier: License :: OSI Approved :: MIT License
Classifier: Natural Language :: English
Classifier: Operating System :: Unix
Classifier: Programming Language :: Python :: 3
Classifier: Programming Language :: Python :: 3.5
Classifier: Programming Language :: Python :: 3.6
Classifier: Programming Language :: Python :: Implementation :: CPython
Classifier: Programming Language :: Python :: Implementation :: PyPy
Classifier: Topic :: Internet :: WWW/HTTP
Classifier: Topic :: Internet :: WWW/HTTP :: Dynamic Content
Classifier: Topic :: Internet :: WWW/HTTP :: Indexing/Search
Classifier: Topic :: Software Development :: Libraries
Classifier: Topic :: Text Processing :: Filters
